setup.py
distributions_test_package/Binomialdistribution.py
distributions_test_package/Gaussiandistribution.py
distributions_test_package/Generaldistribution.py
distributions_test_package/__init__.py
distributions_test_package.egg-info/PKG-INFO
distributions_test_package.egg-info/SOURCES.txt
distributions_test_package.egg-info/dependency_links.txt
distributions_test_package.egg-info/not-zip-safe
distributions_test_package.egg-info/top_level.txt