Metadata-Version: 1.0
Name: distributions-test-package
Version: 0.1
Summary: Gaussian distributions
Home-page: UNKNOWN
Author: Julien Jaber
Author-email: julien-jaber@hotmail.com
License: UNKNOWN
Platform: UNKNOWN
